{
  "variants": [
    "weekly",
    "lts"
  ],
  "weekly": {
    "filename": "binary/jenkins_2.543_all.deb",
    "sha256": "efebe52e29f835deceab16599909afc37ff08527ff1c6df36ab9e870aa0d1921",
    "url": "https://pkg.jenkins.io/debian/binary/jenkins_2.543_all.deb",
    "version": "2.543",
    "repo": "https://pkg.jenkins.io/debian"
  },
  "lts": {
    "filename": "binary/jenkins_2.528.3_all.deb",
    "sha256": "64f12f67d59fe4df7ca40863b58b78f95f5c36352f59b688a023f9f1a759d13b",
    "url": "https://pkg.jenkins.io/debian-stable/binary/jenkins_2.528.3_all.deb",
    "version": "2.528.3",
    "repo": "https://pkg.jenkins.io/debian-stable"
  }
}
