{
  "variants": [
    "weekly",
    "lts"
  ],
  "weekly": {
    "filename": "binary/jenkins_2.525_all.deb",
    "sha256": "f697143f3e496011d657bc5d57953ff3c44afe5f8b06ad207db19b9d018fbda2",
    "url": "https://pkg.jenkins.io/debian/binary/jenkins_2.525_all.deb",
    "version": "2.525",
    "repo": "https://pkg.jenkins.io/debian"
  },
  "lts": {
    "filename": "binary/jenkins_2.516.2_all.deb",
    "sha256": "aae1fa66ef3e979d715d24dc0c135670fc5a2b488644a46c335bf9ac40be86c1",
    "url": "https://pkg.jenkins.io/debian-stable/binary/jenkins_2.516.2_all.deb",
    "version": "2.516.2",
    "repo": "https://pkg.jenkins.io/debian-stable"
  }
}
